MANIFEST.in
README.rst
RELEASE-VERSION
mqtt-watchdir.py
setup.py
version.py
mqtt_watchdir.egg-info/PKG-INFO
mqtt_watchdir.egg-info/SOURCES.txt
mqtt_watchdir.egg-info/dependency_links.txt
mqtt_watchdir.egg-info/requires.txt
mqtt_watchdir.egg-info/top_level.txt