Metadata-Version: 1.1
Name: mqtt-watchdir
Version: 2.0-10-g926c526
Summary: Recursively watch a directory for modifications and publish file content to an MQTT broker
Home-page: https://github.com/jpmens/mqtt-watchdir
Author: Jan-Piet Mens
Author-email: jpmens@gmail.com
License: BSD License
Keywords: MQTT,files,notify
Platform: UNKNOWN
Classifier: Development Status :: 4 - Beta
Classifier: Intended Audience :: Developers
Classifier: License :: OSI Approved :: BSD License
Classifier: Operating System :: MacOS :: MacOS X
Classifier: Operating System :: POSIX
Classifier: Programming Language :: Python
Classifier: Programming Language :: Python :: 2.6
Classifier: Programming Language :: Python :: 2.7
Classifier: Topic :: Communications
Classifier: Topic :: Internet
